{
  "results": [
    {
      "repository": "https://github.com/junit-team/junit4.git",
      "sha1": "6ba9c4dc1e71e9ceb2e35991e8fc0e4aee69ad6e",
      "url": "https://github.com/junit-team/junit4/commit/6ba9c4dc1e71e9ceb2e35991e8fc0e4aee69ad6e",
      "commonMatching": [
        {
          "leftSideLocation": {
            "container": "org.junit.runner.JUnitCore",
            "type": "Method",
            "name": "main",
            "filePath": "src/main/java/org/junit/runner/JUnitCore.java",
            "startLine": 27,
            "endLine": 38,
            "startColumn": 5,
            "endColumn": 6
          },
          "rightSideLocation": {
            "container": "org.junit.runner.JUnitCore",
            "type": "Method",
            "name": "main",
            "filePath": "src/main/java/org/junit/runner/JUnitCore.java",
            "startLine": 27,
            "endLine": 37,
            "startColumn": 5,
            "endColumn": 6
          },
          "validation": true
        },
        {
          "leftSideLocation": {
            "container": "org.junit.runner.JUnitCore",
            "type": "Class",
            "name": "JUnitCore",
            "filePath": "src/main/java/org/junit/runner/JUnitCore.java",
            "startLine": 11,
            "endLine": 167,
            "startColumn": 0,
            "endColumn": 2
          },
          "rightSideLocation": {
            "container": "org.junit.runner.JUnitCore",
            "type": "Class",
            "name": "JUnitCore",
            "filePath": "src/main/java/org/junit/runner/JUnitCore.java",
            "startLine": 11,
            "endLine": 171,
            "startColumn": 0,
            "endColumn": 2
          },
          "validation": true
        },
        {
          "leftSideLocation": {
            "container": "org.junit.tests.running.core.CommandLineTest",
            "type": "Method",
            "name": "runATest",
            "filePath": "src/test/java/org/junit/tests/running/core/CommandLineTest.java",
            "startLine": 38,
            "endLine": 47,
            "startColumn": 5,
            "endColumn": 6
          },
          "rightSideLocation": {
            "container": "org.junit.tests.running.core.CommandLineTest",
            "type": "Method",
            "name": "runATest",
            "filePath": "src/test/java/org/junit/tests/running/core/CommandLineTest.java",
            "startLine": 39,
            "endLine": 44,
            "startColumn": 5,
            "endColumn": 6
          },
          "validation": true
        },
        {
          "leftSideLocation": {
            "container": "org.junit.tests.running.core.CommandLineTest",
            "type": "Class",
            "name": "CommandLineTest",
            "filePath": "src/test/java/org/junit/tests/running/core/CommandLineTest.java",
            "startLine": 14,
            "endLine": 78,
            "startColumn": 0,
            "endColumn": 2
          },
          "rightSideLocation": {
            "container": "org.junit.tests.running.core.CommandLineTest",
            "type": "Class",
            "name": "CommandLineTest",
            "filePath": "src/test/java/org/junit/tests/running/core/CommandLineTest.java",
            "startLine": 15,
            "endLine": 75,
            "startColumn": 0,
            "endColumn": 2
          },
          "validation": true
        },
        {
          "leftSideLocation": {
            "container": "org.junit.tests.running.core.JUnitCoreReturnsCorrectExitCodeTest",
            "type": "Method",
            "name": "runClass",
            "filePath": "src/test/java/org/junit/tests/running/core/JUnitCoreReturnsCorrectExitCodeTest.java",
            "startLine": 39,
            "endLine": 46,
            "startColumn": 5,
            "endColumn": 6
          },
          "rightSideLocation": {
            "container": "org.junit.tests.running.core.JUnitCoreReturnsCorrectExitCodeTest",
            "type": "Method",
            "name": "runClass",
            "filePath": "src/test/java/org/junit/tests/running/core/JUnitCoreReturnsCorrectExitCodeTest.java",
            "startLine": 39,
            "endLine": 42,
            "startColumn": 5,
            "endColumn": 6
          },
          "validation": true
        },
        {
          "leftSideLocation": {
            "container": "org.junit.tests.running.core.JUnitCoreReturnsCorrectExitCodeTest",
            "type": "Class",
            "name": "JUnitCoreReturnsCorrectExitCodeTest",
            "filePath": "src/test/java/org/junit/tests/running/core/JUnitCoreReturnsCorrectExitCodeTest.java",
            "startLine": 9,
            "endLine": 47,
            "startColumn": 0,
            "endColumn": 2
          },
          "rightSideLocation": {
            "container": "org.junit.tests.running.core.JUnitCoreReturnsCorrectExitCodeTest",
            "type": "Class",
            "name": "JUnitCoreReturnsCorrectExitCodeTest",
            "filePath": "src/test/java/org/junit/tests/running/core/JUnitCoreReturnsCorrectExitCodeTest.java",
            "startLine": 9,
            "endLine": 43,
            "startColumn": 0,
            "endColumn": 2
          },
          "validation": true
        },
        {
          "leftSideLocation": {
            "container": "public main(args String...) : void",
            "type": "Statement",
            "name": "System.exit(result.wasSuccessful() ? 0 : 1);\n",
            "filePath": "src/main/java/org/junit/runner/JUnitCore.java",
            "startLine": 37,
            "endLine": 37,
            "startColumn": 9,
            "endColumn": 53
          },
          "rightSideLocation": {
            "container": "package runMain(args String[]) : int",
            "type": "Statement",
            "name": "return result.wasSuccessful() ? 0 : 1;\n",
            "filePath": "src/main/java/org/junit/runner/JUnitCore.java",
            "startLine": 41,
            "endLine": 41,
            "startColumn": 9,
            "endColumn": 47
          },
          "validation": true
        },
        {
          "leftSideLocation": {
            "container": "private runClass(className String, returnCode int) : void",
            "type": "Statement",
            "name": "assertEquals(Integer.valueOf(returnCode),exitValue);\n",
            "filePath": "src/test/java/org/junit/tests/running/core/JUnitCoreReturnsCorrectExitCodeTest.java",
            "startLine": 45,
            "endLine": 45,
            "startColumn": 9,
            "endColumn": 62
          },
          "rightSideLocation": {
            "container": "private runClass(className String, returnCode int) : void",
            "type": "Statement",
            "name": "assertEquals(returnCode,exitValue);\n",
            "filePath": "src/test/java/org/junit/tests/running/core/JUnitCoreReturnsCorrectExitCodeTest.java",
            "startLine": 41,
            "endLine": 41,
            "startColumn": 9,
            "endColumn": 45
          },
          "validation": true
        }
      ],
      "ourApproach": [
        {
          "leftSideLocation": {
            "container": "org.junit.tests.running.core.MainRunner",
            "type": "Method",
            "name": "runWithCheckForSystemExit",
            "filePath": "src/test/java/org/junit/tests/running/core/MainRunner.java",
            "startLine": 42,
            "endLine": 66,
            "startColumn": 5,
            "endColumn": 6
          },
          "rightSideLocation": {
            "container": "org.junit.runner.MainRunner",
            "type": "Method",
            "name": "runMain",
            "filePath": "src/test/java/org/junit/runner/MainRunner.java",
            "startLine": 8,
            "endLine": 16,
            "startColumn": 5,
            "endColumn": 6
          },
          "validation": true
        },
        {
          "leftSideLocation": {
            "container": "org.junit.tests.running.core.MainRunner",
            "type": "Class",
            "name": "MainRunner",
            "filePath": "src/test/java/org/junit/tests/running/core/MainRunner.java",
            "startLine": 7,
            "endLine": 67,
            "startColumn": 0,
            "endColumn": 2
          },
          "rightSideLocation": {
            "container": "org.junit.runner.MainRunner",
            "type": "Class",
            "name": "MainRunner",
            "filePath": "src/test/java/org/junit/runner/MainRunner.java",
            "startLine": 6,
            "endLine": 23,
            "startColumn": 0,
            "endColumn": 2
          },
          "validation": true
        },
        {
          "leftSideLocation": {
            "container": "public runATest() : void",
            "type": "Statement",
            "name": "new MainRunner().runWithCheckForSystemExit(new Runnable(){\n  public void run(){\n    JUnitCore.main(\"org.junit.tests.running.core.CommandLineTest$Example\");\n  }\n}\n);\n",
            "filePath": "src/test/java/org/junit/tests/running/core/CommandLineTest.java",
            "startLine": 41,
            "endLine": 45,
            "startColumn": 9,
            "endColumn": 12
          },
          "rightSideLocation": {
            "container": "public runATest() : void",
            "type": "Statement",
            "name": "MainRunner.runMain(Example.class.getName());\n",
            "filePath": "src/test/java/org/junit/tests/running/core/CommandLineTest.java",
            "startLine": 42,
            "endLine": 42,
            "startColumn": 9,
            "endColumn": 53
          },
          "validation": true
        },
        {
          "leftSideLocation": {
            "container": "private runClass(className String, returnCode int) : void",
            "type": "Statement",
            "name": "Integer exitValue=new MainRunner().runWithCheckForSystemExit(new Runnable(){\n  public void run(){\n    JUnitCore.main(className);\n  }\n}\n);\n",
            "filePath": "src/test/java/org/junit/tests/running/core/JUnitCoreReturnsCorrectExitCodeTest.java",
            "startLine": 40,
            "endLine": 44,
            "startColumn": 9,
            "endColumn": 12
          },
          "rightSideLocation": {
            "container": "private runClass(className String, returnCode int) : void",
            "type": "Statement",
            "name": "int exitValue=MainRunner.runMain(className);\n",
            "filePath": "src/test/java/org/junit/tests/running/core/JUnitCoreReturnsCorrectExitCodeTest.java",
            "startLine": 40,
            "endLine": 40,
            "startColumn": 9,
            "endColumn": 55
          },
          "validation": true
        },
        {
          "leftSideLocation": {
            "container": "public runWithCheckForSystemExit(runnable Runnable) : Integer",
            "type": "Statement",
            "name": "try",
            "filePath": "src/test/java/org/junit/tests/running/core/MainRunner.java",
            "startLine": 55,
            "endLine": 65,
            "startColumn": 9,
            "endColumn": 10
          },
          "rightSideLocation": {
            "container": "public runMain(args String...) : int",
            "type": "Statement",
            "name": "try",
            "filePath": "src/test/java/org/junit/runner/MainRunner.java",
            "startLine": 11,
            "endLine": 15,
            "startColumn": 9,
            "endColumn": 10
          },
          "validation": true
        },
        {
          "leftSideLocation": {
            "container": "public runWithCheckForSystemExit(runnable Runnable) : Integer",
            "type": "Statement",
            "name": "PrintStream oldOut=System.out;\n",
            "filePath": "src/test/java/org/junit/tests/running/core/MainRunner.java",
            "startLine": 52,
            "endLine": 52,
            "startColumn": 9,
            "endColumn": 41
          },
          "rightSideLocation": {
            "container": "public runMain(args String...) : int",
            "type": "Statement",
            "name": "PrintStream oldOut=System.out;\n",
            "filePath": "src/test/java/org/junit/runner/MainRunner.java",
            "startLine": 9,
            "endLine": 9,
            "startColumn": 9,
            "endColumn": 41
          },
          "validation": true
        },
        {
          "leftSideLocation": {
            "container": "public runWithCheckForSystemExit(runnable Runnable) : Integer",
            "type": "Statement",
            "name": "System.setOut(oldOut);\n",
            "filePath": "src/test/java/org/junit/tests/running/core/MainRunner.java",
            "startLine": 64,
            "endLine": 64,
            "startColumn": 13,
            "endColumn": 35
          },
          "rightSideLocation": {
            "container": "public runMain(args String...) : int",
            "type": "Statement",
            "name": "System.setOut(oldOut);\n",
            "filePath": "src/test/java/org/junit/runner/MainRunner.java",
            "startLine": 14,
            "endLine": 14,
            "startColumn": 13,
            "endColumn": 35
          },
          "validation": true
        },
        {
          "leftSideLocation": {
            "container": "public runWithCheckForSystemExit(runnable Runnable) : Integer",
            "type": "Statement",
            "name": "finally",
            "filePath": "src/test/java/org/junit/tests/running/core/MainRunner.java",
            "startLine": 62,
            "endLine": 65,
            "startColumn": 19,
            "endColumn": 10
          },
          "rightSideLocation": {
            "container": "public runMain(args String...) : int",
            "type": "Statement",
            "name": "finally",
            "filePath": "src/test/java/org/junit/runner/MainRunner.java",
            "startLine": 13,
            "endLine": 15,
            "startColumn": 19,
            "endColumn": 10
          },
          "validation": true
        },
        {
          "leftSideLocation": {
            "container": "public runWithCheckForSystemExit(runnable Runnable) : Integer",
            "type": "Statement",
            "name": "System.setOut(new PrintStream(new ByteArrayOutputStream()));\n",
            "filePath": "src/test/java/org/junit/tests/running/core/MainRunner.java",
            "startLine": 54,
            "endLine": 54,
            "startColumn": 9,
            "endColumn": 69
          },
          "rightSideLocation": {
            "container": "public runMain(args String...) : int",
            "type": "Statement",
            "name": "System.setOut(new PrintStream(new NullOutputStream()));\n",
            "filePath": "src/test/java/org/junit/runner/MainRunner.java",
            "startLine": 10,
            "endLine": 10,
            "startColumn": 9,
            "endColumn": 64
          },
          "validation": true
        }
      ],
      "baseline": [
        {
          "leftSideLocation": {
            "container": "public main(args String...) : void",
            "type": "Statement",
            "name": "System.exit(result.wasSuccessful() ? 0 : 1);\n",
            "filePath": "src/main/java/org/junit/runner/JUnitCore.java",
            "startLine": 37,
            "endLine": 37,
            "startColumn": 9,
            "endColumn": 53
          },
          "rightSideLocation": {
            "container": "public main(args String...) : void",
            "type": "Statement",
            "name": "System.exit(runMain(args));\n",
            "filePath": "src/main/java/org/junit/runner/JUnitCore.java",
            "startLine": 36,
            "endLine": 36,
            "startColumn": 9,
            "endColumn": 36
          },
          "validation": false
        }
      ]
    },
    {
      "repository": "https://github.com/junit-team/junit4.git",
      "sha1": "43df829aeef59d65b951a1eff3daf3c6fadbaee1",
      "url": "https://github.com/junit-team/junit4/commit/43df829aeef59d65b951a1eff3daf3c6fadbaee1",
      "commonMatching": [
        {
          "leftSideLocation": {
            "container": "org.junit.runners.model.FrameworkMember",
            "type": "Method",
            "name": "handlePossibleBridgeMethod",
            "filePath": "src/main/java/org/junit/runners/model/FrameworkMember.java",
            "startLine": 15,
            "endLine": 35,
            "startColumn": 5,
            "endColumn": 6
          },
          "rightSideLocation": {
            "container": "org.junit.runners.model.FrameworkMember",
            "type": "Method",
            "name": "handlePossibleBridgeMethod",
            "filePath": "src/main/java/org/junit/runners/model/FrameworkMember.java",
            "startLine": 15,
            "endLine": 38,
            "startColumn": 5,
            "endColumn": 6
          },
          "validation": true
        },
        {
          "leftSideLocation": {
            "container": "org.junit.runners.model.FrameworkMember",
            "type": "Class",
            "name": "FrameworkMember",
            "filePath": "src/main/java/org/junit/runners/model/FrameworkMember.java",
            "startLine": 6,
            "endLine": 60,
            "startColumn": 0,
            "endColumn": 2
          },
          "rightSideLocation": {
            "container": "org.junit.runners.model.FrameworkMember",
            "type": "Class",
            "name": "FrameworkMember",
            "filePath": "src/main/java/org/junit/runners/model/FrameworkMember.java",
            "startLine": 6,
            "endLine": 63,
            "startColumn": 0,
            "endColumn": 2
          },
          "validation": true
        }
      ],
      "ourApproach": [
        {
          "leftSideLocation": {
            "container": "package handlePossibleBridgeMethod(members List<T>) : T",
            "type": "Statement",
            "name": "return (T)this;\n",
            "filePath": "src/main/java/org/junit/runners/model/FrameworkMember.java",
            "startLine": 34,
            "endLine": 34,
            "startColumn": 9,
            "endColumn": 25
          },
          "rightSideLocation": {
            "container": "package handlePossibleBridgeMethod(members List<T>) : T",
            "type": "Statement",
            "name": "return result;\n",
            "filePath": "src/main/java/org/junit/runners/model/FrameworkMember.java",
            "startLine": 37,
            "endLine": 37,
            "startColumn": 9,
            "endColumn": 23
          },
          "validation": true
        }
      ],
      "baseline": [
        {
          "leftSideLocation": {
            "container": "package handlePossibleBridgeMethod(members List<T>) : T",
            "type": "Statement",
            "name": "return (T)this;\n",
            "filePath": "src/main/java/org/junit/runners/model/FrameworkMember.java",
            "startLine": 34,
            "endLine": 34,
            "startColumn": 9,
            "endColumn": 25
          },
          "rightSideLocation": {
            "container": "package handlePossibleBridgeMethod(members List<T>) : T",
            "type": "Statement",
            "name": "@SuppressWarnings(\"unchecked\") T result=(T)thisMember;\n",
            "filePath": "src/main/java/org/junit/runners/model/FrameworkMember.java",
            "startLine": 34,
            "endLine": 35,
            "startColumn": 9,
            "endColumn": 35
          },
          "validation": false
        }
      ]
    },
    {
      "repository": "https://github.com/junit-team/junit4.git",
      "sha1": "02aaa01b8f74c0eb496d76685ec49fddeb311087",
      "url": "https://github.com/junit-team/junit4/commit/02aaa01b8f74c0eb496d76685ec49fddeb311087",
      "commonMatching": [
        {
          "leftSideLocation": {
            "container": "org.junit.internal.runners.statements.FailOnTimeoutTest",
            "type": "Method",
            "name": "statementThatCanBeInterruptedIsStoppedAfterTimeout",
            "filePath": "src/test/java/org/junit/internal/runners/statements/FailOnTimeoutTest.java",
            "startLine": 115,
            "endLine": 130,
            "startColumn": 5,
            "endColumn": 6
          },
          "rightSideLocation": {
            "container": "org.junit.internal.runners.statements.FailOnTimeoutTest",
            "type": "Method",
            "name": "statementThatCanBeInterruptedIsStoppedAfterTimeout",
            "filePath": "src/test/java/org/junit/internal/runners/statements/FailOnTimeoutTest.java",
            "startLine": 117,
            "endLine": 130,
            "startColumn": 5,
            "endColumn": 6
          },
          "validation": true
        },
        {
          "leftSideLocation": {
            "container": "org.junit.internal.runners.statements.FailOnTimeoutTest.DelegatingStatement",
            "type": "Field",
            "name": "delegate",
            "filePath": "src/test/java/org/junit/internal/runners/statements/FailOnTimeoutTest.java",
            "startLine": 246,
            "endLine": 246,
            "startColumn": 19,
            "endColumn": 27
          },
          "rightSideLocation": {
            "container": "org.junit.internal.runners.statements.FailOnTimeoutTest.DelegatingStatement",
            "type": "Field",
            "name": "delegate",
            "filePath": "src/test/java/org/junit/internal/runners/statements/FailOnTimeoutTest.java",
            "startLine": 246,
            "endLine": 246,
            "startColumn": 28,
            "endColumn": 36
          },
          "validation": true
        },
        {
          "leftSideLocation": {
            "container": "org.junit.internal.runners.statements.FailOnTimeoutTest.DelegatingStatement",
            "type": "Class",
            "name": "DelegatingStatement",
            "filePath": "src/test/java/org/junit/internal/runners/statements/FailOnTimeoutTest.java",
            "startLine": 245,
            "endLine": 252,
            "startColumn": 5,
            "endColumn": 6
          },
          "rightSideLocation": {
            "container": "org.junit.internal.runners.statements.FailOnTimeoutTest.DelegatingStatement",
            "type": "Class",
            "name": "DelegatingStatement",
            "filePath": "src/test/java/org/junit/internal/runners/statements/FailOnTimeoutTest.java",
            "startLine": 245,
            "endLine": 252,
            "startColumn": 5,
            "endColumn": 6
          },
          "validation": true
        },
        {
          "leftSideLocation": {
            "container": "org.junit.internal.runners.statements.FailOnTimeoutTest.RunForASecond",
            "type": "Method",
            "name": "evaluate",
            "filePath": "src/test/java/org/junit/internal/runners/statements/FailOnTimeoutTest.java",
            "startLine": 263,
            "endLine": 270,
            "startColumn": 9,
            "endColumn": 10
          },
          "rightSideLocation": {
            "container": "org.junit.internal.runners.statements.FailOnTimeoutTest.RunForASecond",
            "type": "Method",
            "name": "evaluate",
            "filePath": "src/test/java/org/junit/internal/runners/statements/FailOnTimeoutTest.java",
            "startLine": 263,
            "endLine": 269,
            "startColumn": 9,
            "endColumn": 10
          },
          "validation": true
        },
        {
          "leftSideLocation": {
            "container": "org.junit.internal.runners.statements.FailOnTimeoutTest.RunForASecond",
            "type": "Class",
            "name": "RunForASecond",
            "filePath": "src/test/java/org/junit/internal/runners/statements/FailOnTimeoutTest.java",
            "startLine": 260,
            "endLine": 271,
            "startColumn": 5,
            "endColumn": 6
          },
          "rightSideLocation": {
            "container": "org.junit.internal.runners.statements.FailOnTimeoutTest.RunForASecond",
            "type": "Class",
            "name": "RunForASecond",
            "filePath": "src/test/java/org/junit/internal/runners/statements/FailOnTimeoutTest.java",
            "startLine": 260,
            "endLine": 270,
            "startColumn": 5,
            "endColumn": 6
          },
          "validation": true
        },
        {
          "leftSideLocation": {
            "container": "org.junit.internal.runners.statements.FailOnTimeoutTest",
            "type": "Class",
            "name": "FailOnTimeoutTest",
            "filePath": "src/test/java/org/junit/internal/runners/statements/FailOnTimeoutTest.java",
            "startLine": 33,
            "endLine": 272,
            "startColumn": 0,
            "endColumn": 2
          },
          "rightSideLocation": {
            "container": "org.junit.internal.runners.statements.FailOnTimeoutTest",
            "type": "Class",
            "name": "FailOnTimeoutTest",
            "filePath": "src/test/java/org/junit/internal/runners/statements/FailOnTimeoutTest.java",
            "startLine": 35,
            "endLine": 271,
            "startColumn": 0,
            "endColumn": 2
          },
          "validation": true
        }
      ],
      "ourApproach": [
        {
          "leftSideLocation": {
            "container": "org.junit.internal.runners.statements.FailOnTimeoutTest.RunForASecond",
            "type": "Field",
            "name": "stillExecuting",
            "filePath": "src/test/java/org/junit/internal/runners/statements/FailOnTimeoutTest.java",
            "startLine": 261,
            "endLine": 261,
            "startColumn": 29,
            "endColumn": 65
          },
          "rightSideLocation": {
            "container": "org.junit.internal.runners.statements.FailOnTimeoutTest.RunForASecond",
            "type": "Field",
            "name": "finished",
            "filePath": "src/test/java/org/junit/internal/runners/statements/FailOnTimeoutTest.java",
            "startLine": 261,
            "endLine": 261,
            "startColumn": 30,
            "endColumn": 62
          },
          "validation": false
        },
        {
          "leftSideLocation": {
            "container": "public evaluate() : void",
            "type": "Statement",
            "name": "while(currentTimeMillis() < timeout)",
            "filePath": "src/test/java/org/junit/internal/runners/statements/FailOnTimeoutTest.java",
            "startLine": 266,
            "endLine": 269,
            "startColumn": 13,
            "endColumn": 14
          },
          "rightSideLocation": {
            "container": "public evaluate() : void",
            "type": "Statement",
            "name": "while(!interrupted() && currentTimeMillis() < timeout)",
            "filePath": "src/test/java/org/junit/internal/runners/statements/FailOnTimeoutTest.java",
            "startLine": 266,
            "endLine": 267,
            "startColumn": 13,
            "endColumn": 14
          },
          "validation": true
        }
      ],
      "baseline": []
    }
  ]
}